slbb_armstr/__init__.py
slbb_armstr/armstrongNo.py
slbb_armstr-0.0.1.dist-info/METADATA
slbb_armstr-0.0.1.dist-info/WHEEL
slbb_armstr-0.0.1.dist-info/license.txt
slbb_armstr-0.0.1.dist-info/top_level.txt
slbb_armstr-0.0.1.dist-info/RECORD
